README.md
setup.py
generic_storage/__init__.py
generic_storage.egg-info/PKG-INFO
generic_storage.egg-info/SOURCES.txt
generic_storage.egg-info/dependency_links.txt
generic_storage.egg-info/requires.txt
generic_storage.egg-info/top_level.txt
generic_storage/storage/LocalStorage.py
generic_storage/storage/S3Storage.py
generic_storage/storage/StorageStrategy.py
generic_storage/storage/__init__.py