Metadata-Version: 1.1
Name: generic-storage
Version: 0.0.3
Summary: Tools for extract sensitive configuration out of your project
Home-page: https://github.com/davidNHK/secret-storage
Author: David Ng
Author-email: david.ng.dev@gmail.com
License: BSD
Download-URL: https://github.com/davidNHK/generic-storage/archive/0.0.3.zip
Keywords: generic-storage,secret-data
Platform: UNKNOWN
